kozmoai_economy/__init__.py
kozmoai_economy/economy_router.py
kozmoai_economy/economy_views.py
kozmoai_economy/gdp/gdp_router.py
kozmoai_economy/py.typed
kozmoai_economy/survey/survey_router.py
kozmoai_economy-1.4.0.dev202506081902.dist-info/METADATA
kozmoai_economy-1.4.0.dev202506081902.dist-info/WHEEL
kozmoai_economy-1.4.0.dev202506081902.dist-info/entry_points.txt
kozmoai_economy-1.4.0.dev202506081902.dist-info/RECORD
